atriumsports/__init__.py
atriumsports/atrium_response.py
atriumsports/endpoints.py
atriumsports/datacore/__init__.py
atriumsports/datacore/datacore.py
atriumsports/datacore/openapi/__init__.py
atriumsports/datacore/openapi/api_client.py
atriumsports/datacore/openapi/api_response.py
atriumsports/datacore/openapi/configuration.py
atriumsports/datacore/openapi/exceptions.py
atriumsports/datacore/openapi/py.typed
atriumsports/datacore/openapi/rest.py
atriumsports/datacore/openapi/api/__init__.py
atriumsports/datacore/openapi/api/awards_api.py
atriumsports/datacore/openapi/api/career_statistics_api.py
atriumsports/datacore/openapi/api/change_log_api.py
atriumsports/datacore/openapi/api/competition_external_ids_api.py
atriumsports/datacore/openapi/api/competition_statistics_api.py
atriumsports/datacore/openapi/api/competitions_api.py
atriumsports/datacore/openapi/api/conduct_api.py
atriumsports/datacore/openapi/api/conference_external_ids_api.py
atriumsports/datacore/openapi/api/conferences_divisions_api.py
atriumsports/datacore/openapi/api/division_external_ids_api.py
atriumsports/datacore/openapi/api/download_video_api.py
atriumsports/datacore/openapi/api/entities_api.py
atriumsports/datacore/openapi/api/entity_external_ids_api.py
atriumsports/datacore/openapi/api/entity_fixture_history_api.py
atriumsports/datacore/openapi/api/entity_fixture_statistics_api.py
atriumsports/datacore/openapi/api/entity_group_external_ids_api.py
atriumsports/datacore/openapi/api/entity_groups_api.py
atriumsports/datacore/openapi/api/fixture_entities_api.py
atriumsports/datacore/openapi/api/fixture_external_ids_api.py
atriumsports/datacore/openapi/api/fixture_external_playbyplay_api.py
atriumsports/datacore/openapi/api/fixture_live_summary_api.py
atriumsports/datacore/openapi/api/fixture_persons_api.py
atriumsports/datacore/openapi/api/fixture_playbyplay_api.py
atriumsports/datacore/openapi/api/fixture_profiles_api.py
atriumsports/datacore/openapi/api/fixture_progressions_api.py
atriumsports_sdk-2.2.0.dist-info/licenses/LICENSE
atriumsports_sdk-2.2.0.dist-info/METADATA
atriumsports_sdk-2.2.0.dist-info/WHEEL
atriumsports_sdk-2.2.0.dist-info/top_level.txt
atriumsports_sdk-2.2.0.dist-info/RECORD
