Metadata-Version: 2.4
Name: atriumsports_sdk
Version: 2.2.0
Summary: Python module for integration to Atrium Sports APIs
Author-email: Atrium Sports <python_dev@atriumsports.com>
License: MIT License
Classifier: Programming Language :: Python :: 3
Classifier: License :: OSI Approved :: MIT License
Classifier: Operating System :: OS Independent
Requires-Python: >=3.9
License-File: LICENSE
Requires-Dist: requests
Requires-Dist: paho-mqtt>=2.1.0
Requires-Dist: python-dateutil>=2.8.2
Requires-Dist: urllib3<3.0.0,>=2.1.0
Requires-Dist: pydantic>=2
Requires-Dist: typing-extensions>=4.7.1
Requires-Dist: aenum>=3.1.11
Requires-Dist: pyjwt>=2.8.0
Provides-Extra: dev
Requires-Dist: ruff; extra == "dev"
Requires-Dist: build; extra == "dev"
Requires-Dist: twine; extra == "dev"
Requires-Dist: pytest; extra == "dev"
Requires-Dist: requests-mock; extra == "dev"
Requires-Dist: pytest-cov>=7.0.0; extra == "dev"
Dynamic: license-file
